alphagenome/__init__.py
alphagenome/colab_utils.py
alphagenome/colab_utils_test.py
alphagenome/tensor_utils.py
alphagenome/tensor_utils_benchmark_test.py
alphagenome/tensor_utils_test.py
alphagenome/typing.py
alphagenome/typing_test.py
alphagenome/data/__init__.py
alphagenome/data/fold_intervals.py
alphagenome/data/fold_intervals_test.py
alphagenome/data/gene_annotation.py
alphagenome/data/gene_annotation_test.py
alphagenome/data/genome.py
alphagenome/data/genome_test.py
alphagenome/data/junction_data.py
alphagenome/data/junction_data_test.py
alphagenome/data/ontology.py
alphagenome/data/ontology_test.py
alphagenome/data/track_data.py
alphagenome/data/track_data_test.py
alphagenome/data/transcript.py
alphagenome/interpretation/__init__.py
alphagenome/interpretation/ism.py
alphagenome/interpretation/ism_test.py
alphagenome/models/__init__.py
alphagenome/models/dna_client.py
alphagenome/models/dna_client_test.py
alphagenome/models/dna_model.py
alphagenome/models/dna_model_test.py
alphagenome/models/dna_output.py
alphagenome/models/dna_output_test.py
alphagenome/models/interval_scorers.py
alphagenome/models/interval_scorers_test.py
alphagenome/models/junction_data_utils.py
alphagenome/models/junction_data_utils_test.py
alphagenome/models/track_data_utils.py
alphagenome/models/track_data_utils_test.py
alphagenome/models/variant_scorers.py
alphagenome/models/variant_scorers_test.py
alphagenome/protos/__init__.py
alphagenome/protos/dna_model.proto
alphagenome/protos/dna_model_pb2.py
alphagenome/protos/dna_model_pb2_grpc.py
alphagenome/protos/dna_model_service.proto
alphagenome/protos/dna_model_service_pb2.py
alphagenome/protos/dna_model_service_pb2_grpc.py
alphagenome/protos/tensor.proto
alphagenome/protos/tensor_pb2.py
alphagenome/protos/tensor_pb2_grpc.py
alphagenome/visualization/__init__.py
alphagenome/visualization/plot.py
alphagenome/visualization/plot_components.py
alphagenome/visualization/plot_components_test.py
alphagenome/visualization/plot_transcripts.py
alphagenome-0.5.1.dist-info/METADATA
alphagenome-0.5.1.dist-info/WHEEL
alphagenome-0.5.1.dist-info/licenses/LICENSE
alphagenome-0.5.1.dist-info/RECORD
