Metadata-Version: 2.4
Name: alphagenome
Version: 0.5.1
Summary: A Python SDK for interacting and visualizing genomic models.
Project-URL: Repository, https://github.com/google-deepmind/alphagenome
Project-URL: Documentation, https://www.alphagenomedocs.com/
Author: Google LLC
Author-email: alphagenome@google.com
License: 
License-File: LICENSE
Keywords: genomics,machine learning,python
Classifier: Development Status :: 4 - Beta
Classifier: Environment :: Console
Classifier: Intended Audience :: Science/Research
Classifier: License :: OSI Approved :: Apache Software License
Classifier: Operating System :: OS Independent
Classifier: Programming Language :: Python :: 3.10
Classifier: Programming Language :: Python :: 3.11
Classifier: Programming Language :: Python :: 3.12
Classifier: Programming Language :: Python :: 3.13
Classifier: Topic :: Scientific/Engineering :: Artificial Intelligence
Requires-Python: >=3.10
Requires-Dist: absl-py
Requires-Dist: anndata
Requires-Dist: grpcio>=1.67.1
Requires-Dist: immutabledict
Requires-Dist: intervaltree
Requires-Dist: jaxtyping
Requires-Dist: matplotlib
Requires-Dist: ml-dtypes
Requires-Dist: numpy
Requires-Dist: pandas
Requires-Dist: protobuf>=5.28.3
Requires-Dist: pyarrow
Requires-Dist: scipy
Requires-Dist: seaborn
Requires-Dist: tqdm
Requires-Dist: typeguard
Requires-Dist: typing-extensions
Requires-Dist: zstandard
Provides-Extra: dev
Requires-Dist: hatch; extra == 'dev'
Provides-Extra: docs
Requires-Dist: ipykernel; extra == 'docs'
Requires-Dist: ipython; extra == 'docs'
Requires-Dist: myst-nb; extra == 'docs'
Requires-Dist: sphinx-autodoc-typehints; extra == 'docs'
Requires-Dist: sphinx-book-theme; extra == 'docs'
Requires-Dist: sphinx-copybutton; extra == 'docs'
Requires-Dist: sphinx-design; extra == 'docs'
Requires-Dist: sphinx-remove-toctrees; extra == 'docs'
Requires-Dist: sphinx>=5.0; extra == 'docs'
Requires-Dist: sphinxcontrib-bibtex>=1.0.0; extra == 'docs'
Provides-Extra: scripts
Requires-Dist: absl-py; extra == 'scripts'
Requires-Dist: pyarrow; extra == 'scripts'
Requires-Dist: pyranges; extra == 'scripts'
